Unhinged/__init__.py
Unhinged/executable.py
Unhinged/logger.py
unhinged-0.0.2.dist-info/LICENSE
unhinged-0.0.2.dist-info/METADATA
unhinged-0.0.2.dist-info/WHEEL
unhinged-0.0.2.dist-info/top_level.txt
unhinged-0.0.2.dist-info/RECORD
