Metadata-Version: 2.1
Name: unhinged
Version: 0.0.2
Summary: A general python executable framework
Home-page: https://github.com/ryanchaiyakul/stickytoe_device
Author: Ryan Chaiyakul
License: UNKNOWN
Platform: UNKNOWN
Classifier: Programming Language :: Python :: 3
Classifier: License :: OSI Approved :: MIT License
Classifier: Operating System :: OS Independent
Requires-Python: >=3.6
Requires-Dist: PyYAML (==5.1.2)
